Workbook

Sheet スケジュール（1日）
B2: ="コースプラン/インストラクションガイド 「"&master!$B$1&"_IG」" -> コースプラン/インストラクションガイド 「AI Native-AWS_IG」
B4: 科目修了条件
B7: スケジュール
C9: 1 日目
A10: 0.39583333 | B10: 0.39583333 | C10: オリエンテーション | G10: ｐ
B11: 0.40625 | C11: =master!B4 -> クラウドとは？
A12: 0.41666667 | G12: ｐ
B13: 0.42708333 | C13: =master!B13 -> AWSとは？
A16: 0.45833333
B17: 0.46875 | C17: =master!B29 -> CDKとは？
A20: 0.5 | B20: 0.5 | C20: =master!B39 -> ガバクラとは？
B22: 0.52083333 | C22: お昼休み
A24: 0.54166667
B26: 0.5625
A28: 0.58333333
A32: 0.625
A36: 0.66666667
A40: 0.70833333
G43: ｐ

Sheet 特記イベント
B2: 特記イベント
B4: 講師の事前準備
B7: 番号 | D7: 講師用資料の保存先 | F7: 配布タイミング | G7: 配布形式
B8: 共通1 | C8: オリエンテーション用資材 | D8: － | F8: 不要 | G8: 電子
C11: テーマ | D11: 主なポイント | G11: 使用教材 | H11: 環境 | I11: 共通 | K11: 実施上のの注意点
I12: 可否 | J12: 時間
C13: オリエンテーション | D13: ・教材のダウンロード ・本科目の概要説明 科目の位置づけや目的、全体スケジュールの説明 | G13: ・共通1 | I13: ○ | J13: 0.010416667

Sheet 講義
B2: 講義
B4: 講師の事前準備
B8: 番号 | C8: 使用教材 | D8: 研修ファイルサーバの保存先 | F8: 配布タイミング | G8: 配布形式
B9: AI-01 | C9: 【AI Native研修-AWS講義】クラウド・AWS入門編_配布用.pptx | D9: － | F9: 済 | G9: 電子
B10: AI-02 | C10: 【AI Native研修-AWS講義】デモ用CDKコード.txt | D10: － | F10: 済 | G10: 電子
B11: AI-03 | C11: ec-site_mock.html | D11: － | F11: 済 | G11: 電子
B13: 章 | C13: テーマ | D13: 主なポイント | G13: 使用教材 | H13: 環境 | I13: 共通 | K13: 実施上の注意点
I14: 可否 | J14: 時間
B15: =master!B4 -> クラウドとは？ | C15: =master!C4 -> １．IT業界の歴史 | D15: IT業界は1970年代にメインフレーム&端末が誕生してから、分散コンピュータまでハードウェアの時代、1990年代からWindowsが誕生してソフトウェアの時代、2000年代からインターネットの時代と遷移した。 通信速度も飛躍的に上昇している。 1994年：Amazonが誕生 2006年：Amazon Web Service（AWS）が誕生してからクラウドの時代が到来し、SaaSが台頭した。 2020年代：からChatGPTなどの生成AIの誕生により、さらに加速度的に成長している。 | G15: ・AI-01 | I15: ○ | J15: 0.0013888889
C16: =master!C5 -> ２．クラウドの市場価値向上 | D16: 生成AIの活用が進む中、クラウドサービスへの支出額は世界的に増加傾向にある。 特に、Amazon、Microsoft、Googleの3社で市場シェアの約7割を占めており、その中でもAmazonは市場シェア・案件数の両面でリーダー的な位置付けとなっている。 また日本においても、これら3社に加えてOracleやさくらインターネットがガバメントクラウドに採用されたことで、官公庁や自治体システムのクラウド移行が加速している。 これにより、クラウドサービスの重要性は今後さらに高まると考えられる。 | G16: ・AI-01 | I16: ○ | J16: 0.0020833333
C17: =master!C6 -> ３．クラウドとは？ | D17: ■オンプレミス サーバーやネットワーク機器、データベースなどのITリソースを自社内のデータセンター等に設置し、構築から運用・保守までを自社で管理する形態。 システム構成やセキュリティ対策を自社の方針に合わせて自由に設計でき、アクセス制御やログ管理なども細かく調整できる。 ■クラウド 外部のクラウドサービス事業者が提供するITリソースを、ネットワーク経由で利用する形態。 自社でハードウェアを保有する必要がなく、必要な時に必要な分だけ利用できるため、初期費用を抑えつつ短期間で導入できる。 | G17: ・AI-01 | I17: ○ | J17: 0.0020833333
C18: =master!C7 -> ４．オンプレミスとのコスト比較 | D18: ■オンプレミスの場合 サーバーを1台設置するだけでも、その周辺に多数のハードウェア機器や設備が必要となるため、初期コストおよび運用コストが非常に高くなる。 ■クラウドの場合 機器や設備を自社で用意する必要がないため、初期投資を大幅に抑えることができ、結果としてコスト削減につながる。 | G18: ・AI-01 | I18: ○ | J18: 0.0020833333
C19: =master!C8 -> ５．クラウドの特徴 | D19: ■俊敏性（アジリティ） ・オンプレミスの場合 自社でデータセンターの確保から機器調達、設置、構築までを行う必要があるため、利用開始までに数か月単位の時間がかかる。 ・クラウドの場合 アカウント作成後にコンソール操作や設定を行うだけで、数分で環境を利用開始できるため、非常に高い俊敏性を持つ。 ■弾力性（スケーラビリティ） ・オンプレミスの場合 繁忙期に合わせてあらかじめ過剰なリソースを用意する必要があり、閑散期にはリソースが余ってしまうという非効率が発生する。 ・クラウドの場合 需要に応じてリソースをスケールアップ・スケールアウトできるため、必要な分だけ利用でき、リソースの無駄を抑えることができる。 | G19: ・AI-01 | I19: ○ | J19: 0.0034722222
C20: =master!C9 -> ６．クラウドの特徴2 | D20: ■幅広い機能 クラウドには多種多様なサービス・機能が用意されており、顧客の業務要件に応じて必要なサービスを組み合わせて柔軟にシステムを構築できる。 ■グローバル展開 主要なパブリッククラウドサービスは、北米・南米・欧州・中東・アフリカ・アジア・オーストラリアなど、世界各地にリージョンを展開している。 また、日本では東京・大阪リージョンを選択することでデータを国内に保持できるため、データ保護や法的要件への対応が可能となる。 | G20: ・AI-01 | I20: ○ | J20: 0.0020833333
C21: =master!C10 -> ７．アベイラビリティゾーンとリージョン | D21: ■アベイラビリティゾーン（AZ） アベイラビリティゾーン（AZ）は、複数のデータセンターから構成される単位であり、冗長化された電力設備や低遅延ネットワークなどによって高い可用性が確保されている。 ※同一AZ内では、1つのデータセンターに障害が発生しても、他のデータセンターが稼働を継続することでサービス全体の継続性が保たれる。 ■リージョン リージョンは、地理的に離れた複数のアベイラビリティゾーン（AZ）から構成される単位であり、大規模な災害や広域障害が発生した場合でも、他のAZを利用することでシステム全体の稼働を継続できるよう設計されている。 ■階層関係 リージョン ＞ アベイラビリティゾーン ＞ データセンター | G21: ・AI-01 | I21: ○ | J21: 0.0020833333
C22: =master!C11 -> ８．クラウドにおける責任共有モデル | D22: ■責任共有モデル 責任共有モデルとは、クラウドにおける「セキュリティ」と「コンプライアンス」の責任を、クラウド事業者とユーザで分担する考え方である。 ※クラウド基盤は複数の層で構成されており、責任範囲はレイヤーごとに異なる。 ・土台となる層（ハードウェア層〜基盤ソフトウェア層） → クラウド事業者の責任範囲 ・その上の層（OS〜アプリケーション、データ層） → ユーザの責任範囲 | G22: ・AI-01 | I22: ○ | J22: 0.0013888889
C23: =master!C12 -> ９．NTTデータはデータセンターが得意 【コラム】 | D23: NTTデータは国内13拠点、海外91拠点にデータセンターを保有し、世界で約6％のシェアを持つデータセンター事業者として、グローバルで第3位に位置している。 | G23: ・AI-01 | I23: ○ | J23: 0.0020833333
B24: =master!B13 -> AWSとは？ | C24: =master!C13 -> 10．AWSとは？ | D24: 米国シアトルに本拠を置くAmazon.comは、世界最大級の総合オンラインストア（ECサイト）を運営するテクノロジー企業である。 同社の事業を支える基盤として提供されているのがAmazon Web Services（AWS）である。AWSは、必要な時に必要な分だけITリソースを低コストで利用できる仕組みを一般ユーザにも提供することで成長した。 このような形態は「パブリッククラウドサービス」と呼ばれ、AWSはその先駆者である。 | G24: ・AI-01 | I24: ○ | J24: 0.0013888889
C25: =master!C14 -> 11．AWSの利用産業 | D25: AWSは製造、金融、政府機関、ゲーム、小売、エネルギーなど、あらゆる産業分野で利用されており、現代の社会基盤を支える存在となっている。 例えば2019年の新型コロナウイルスの流行時には、米国の製薬会社ModernaがAWSの機械学習技術を活用し、ワクチン開発の効率化を実現した。 また日本においても、デジタル庁がAWSを活用し、ワクチン接種証明書のシステムを短期間で構築するなど、行政分野でもクラウドの活用が進んでいる。 このようにAWSは、民間・公共の両分野において重要な役割を果たしている。 | G25: ・AI-01 | I25: ○ | J25: 0.0013888889
C26: =master!C15 -> 12．Web3層アーキテクチャ | D26: ■Web3層構造（Web3層アーキテクチャ） Web3層構造とは、Webアプリケーションを以下の3つの層に分割して設計・構築するシステム構造のことである。 ・プレゼンテーション層（画面・UI） ・アプリケーション層（業務ロジック） ・データ層（データベース） ■3層分離 3層分離とは、Webアプリケーションを設計する際に、上記3つの層を分離して管理する設計手法を指す。 ■メリット 3層を分離することで、各層が独立して機能できるため、他の層に影響を与えずに変更やスケールが可能となる。 その結果、以下のような利点がある。 ・柔軟性の向上 ・セキュリティの向上 ・保守・管理の容易化 | G26: ・AI-01 | I26: ○ | J26: 0.0034722222
C27: =master!C16 -> 13．AWSの基本アーキテクチャ | D27: AWS上にWeb3層構造のシステムを構築する場合、基本的なアーキテクチャとして以下のサービスが利用される。 ■ネットワーク層 ・Amazon VPC（Virtual Private Cloud）：AWS上に構築する仮想ネットワーク環境 ■アプリケーション層 ・Amazon EC2（Elastic Compute Cloud）：アプリケーションを実行する仮想サーバー ・ELB（Elastic Load Balancing）：複数のEC2にトラフィックを分散するロードバランサー ■データ層 ・Amazon RDS（Relational Database Service）：リレーショナルデータベースサービス ・Amazon S3（Simple Storage Service）：オブジェクトストレージ（ファイル保存など） ■運用・監視 ・Amazon CloudWatch：システムの監視、ログ収集、アラーム設定などを行うサービス | G27: ・AI-01 | I27: ○ | J27: 0.0020833333
C28: =master!C17 -> 14．Amazon VPC（Virtual Private Cloud） | D28: Amazon VPCは、ユーザーごとに論理的に分離された仮想ネットワーク環境である。 オンプレミス環境における「DMZ（非武装地帯）」や「イントラネット（社内ネットワーク）」に相当する概念として扱われる。 VPCはリージョン単位で作成され、その中に複数のアベイラビリティゾーン（AZ）を配置することができる。さらに各AZ内で、パブリックサブネットやプライベートサブネットに分割してネットワークを設計することが可能である。 ■階層構造の関係 リージョン ＞ VPC ＞ アベイラビリティゾーン（AZ） ＞ サブネット ＞ リソース（EC2など） | G28: ・AI-01 | I28: ○ | J28: 0.0020833333
C29: =master!C18 -> 15．Amazon EC2（Elastic Compute Cloud） | D29: Amazon EC2は、クラウド上で提供される仮想サーバーサービスであり、オンプレミスにおける「物理サーバー」に相当する。 仮想サーバーとは、1台の物理サーバーを論理的に分割し、複数のサーバーとして独立して利用できる仕組みである。 EC2は数分で起動でき、利用した分だけ課金される従量課金モデル（秒単位課金など）で提供される。 また、WindowsやLinuxなど複数のOSに対応しており、必要なソフトウェアを自由にインストールして利用できる。 さらに、利用状況に応じて以下のような柔軟な変更が可能である。 ・スケールアップ／ダウン（性能の変更） ・スケールアウト／イン（台数の増減） ・オートスケーリング（自動調整） | G29: ・AI-01 | I29: ○ | J29: 0.0020833333
C30: =master!C19 -> 16．Amazon RDS（Relational Database Service） | D30: Amazon RDSは、クラウド上で提供されるマネージド型のリレーショナルデータベースサービスであり、オンプレミスにおける「リレーショナルデータベースサーバー」に相当する。 MySQL、Oracle、SQL Server、PostgreSQL、MariaDB、Auroraなどの主要なデータベースエンジンから選択して利用できる。 ■可用性・耐障害性 待機系（スタンバイ）を複数のアベイラビリティゾーン（AZ）に分散配置することで、障害発生時でも自動的にフェイルオーバーし、高い可用性を実現できる。 ■運用・保守の効率化 以下の機能により、運用負荷とコストを削減できる。 ・自動バックアップ ・パッチ適用の自動化 ・監視・メンテナンスの簡素化 | G30: ・AI-01 | I30: ○ | J30: 0.0020833333
C31: =master!C20 -> 17．マネージドサービスとは？ | D31: ■オンプレミスの場合 データベースの構築・運用・保守はすべてユーザ側の責任となる。 一方AWSでは、利用形態によって責任範囲が異なる。 ■EC2上にデータベースを構築する場合（IaaS） EC2（仮想サーバー）上にデータベースを構築する場合、インフラ部分はAWSが責任を持つ一方で、OS・ミドルウェア・ データベースの運用はユーザ側の責任となる。 そのため、責任はAWSとユーザで分担される形となる。 ■Amazon RDSを利用する場合（マネージドサービス） Amazon RDSを利用することで、データベースの運用管理の多くがAWS側に移譲される。 これによりユーザ側の責任範囲は主に「アプリケーション層」と「データ管理」に限定される。 このように、マネージドサービスを利用することでユーザの運用負担を大幅に削減できる。これがクラウドにおけるマネージドサービスの大きな特徴であり、システム構築において推奨される理由である。 | G31: ・AI-01 | I31: ○ | J31: 0.0020833333
C32: =master!C21 -> 18．ELB（Elastic Load Balancing） | D32: Elastic Load Balancing（ELB）は、複数のEC2インスタンスなどに対してアクセスを分散し、システム全体の負荷を最適化するサービスである。 ※オンプレミスにおける「ロードバランサー（負荷分散装置）」に相当する。 ■種類 用途に応じて以下の3種類から選択できる。 ・ALB（Application Load Balancer）：HTTP/HTTPSなどアプリケーション層向け ・NLB（Network Load Balancer）：TCP/UDPなど高性能・低遅延向け ・GWLB（Gateway Load Balancer）：ネットワークアプライアンス連携向け ■可用性・スケーラビリティ ELBは複数のアベイラビリティゾーン（AZ）にまたがって配置できるため、高い耐障害性を持つ。 また、アクセス量に応じて自動的にキャパシティが増減し、負荷状況に応じたスケーリングが可能である。 | G32: ・AI-01 | I32: ○ | J32: 0.0020833333
C33: =master!C22 -> 19．Amazon S3（Simple Storage Service） | D33: Amazon S3は、クラウド上で提供されるオブジェクトストレージサービスである。 ※オンプレミスにおける「ネットワークストレージ」に相当する。 ■可用性・耐久性 データは自動的に複数のアベイラビリティゾーン（通常3箇所以上）に分散して保存され、高い耐障害性が確保されている。 データ耐久性は「99.999999999%（イレブンナイン）」とされ、非常に高い信頼性を持つ。 ■容量・性能 ・容量は実質無制限 ・1ファイルの最大サイズは50TB ・データ量に依存せずスケーラブルで安定した性能を提供 ■コスト 従量課金制であり、低コストで利用可能（例：1GBあたり約数円/月程度）。 ■連携性 他のAWSサービス（EC2、Lambda、CloudFrontなど）と柔軟に連携でき、幅広い用途で利用される。 | G33: ・AI-01 | I33: ○ | J33: 0.0020833333
C34: =master!C23 -> 20．Amazon CloudWatch | D34: Amazon CloudWatchは、AWS上に構築されたEC2やRDSなどのリソース、およびアプリケーションを監視・管理するための統合モニタリングサービスである。 システムの稼働状況を可視化し、障害検知から復旧対応までを支援することができる。 ■主な機能 ・メトリクス監視 CPU使用率、ネットワーク通信量などのAWSリソースの稼働状況を数値データとして収集・監視する。 ・ログ収集・分析 アプリケーションログやアクセスログなどを集約し、保存・検索・分析を行うことができる。 ・アラームと自動化 しきい値を設定し、異常発生時にメール通知を行ったり、Auto Scalingや再起動などのアクションを自動実行できる。 ・ダッシュボード 監視データやグラフを1画面に集約し、システム全体の稼働状況を視覚的に把握できる。 | G34: ・AI-01 | I34: ○ | J34: 0.0020833333
C35: =master!C24 -> 21．コンピューティングサービス | D35: ■AWSのコンピューティングサービス AWSには、アプリケーションを実行するためのコンピューティングサービスとして以下が存在する。 ・Amazon EC2（仮想サーバー） ・Amazon ECS／Amazon EKS（コンテナ実行環境） ・AWS Lambda（サーバーレス実行環境） これらは総称して「コンピューティングサービス」と呼ばれる。 ■責任範囲とマネージドレベルの違い これらのサービスは、抽象化レベルが上がるほどAWS側の責任範囲が広がる。 ・EC2：OSやミドルウェア管理などユーザ責任が多い ・コンテナ（ECS/EKS）：実行環境の一部をAWSが管理 ・サーバーレス（Lambda）：インフラ管理をほぼAWSが担う ■メリット（進化の方向性） 仮想サーバー → コンテナ → サーバーレスへと進むほど、以下の利点がある。 ・インフラ管理の負担軽減 ・運用工数の削減 ・アプリケーション開発・リリースの高速化 | G35: ・AI-01 | I35: ○ | J35: 0.0020833333
C36: =master!C25 -> 22．コンテナとは？ | D36: ■コンテナとは コンテナとは、アプリケーションとその実行に必要なライブラリや設定ファイルなどの環境をひとまとめにパッケージ化し、どの環境でも同じように動作させるための仕組みである。 名前の由来は、貨物輸送で使われる「コンテナ」にあり、どの輸送手段でも中身を変えずに運べるという考え方に似ている。 ■仕組み コンテナは、サーバー上のOSを共有しながら、その上にアプリケーションごとに独立した実行環境（小さな隔離領域）を作成する。 これにより、他のアプリケーションの影響を受けずに、安全かつ軽量に動作させることができる。 ■コンテナエンジン コンテナを作成・実行・管理するためのソフトウェアを「コンテナエンジン」と呼ぶ。 コンテナエンジンが、イメージの実行やコンテナの起動・停止などを制御する。 ■特徴・メリット コンテナは仮想サーバー（VM）の進化形とも言われ、以下のメリットがある。 ・環境差異の排除（どこでも同じように動く） ・起動が高速 ・リソース効率が高い ・移植性が高い | G36: ・AI-01 | I36: ○ | J36: 0.0034722222
... C38: =master!C27 -> 24．AWS Lambda | D38: AWS Lambdaは、仮想サーバーやコンテナに続く「サーバーレス」アーキテクチャを実現する代表的なサービスである。 コードをイベント駆動で実行する仕組みを提供しており、実行時のみリソースが割り当てられるため、従量課金で利用できる。 Webアプリケーションとして利用する場合は、Amazon API Gatewayと組み合わせ、HTTPリクエストをトリガーとしてLambdaを実行する構成が一般的である。 ■サーバーレス サーバーレスとは、サーバーの構築・運用・保守・スケーリングをクラウド側が自動的に行う開発・運用モデルである。 ユーザはサーバー管理を意識せず、アプリケーションの開発（コード作成）に専念できる。 | G38: ・AI-01 | I38: ○ | J38: 0.0020833333
C39: =master!C28 -> 25．その他の周辺サービス | G39: ・AI-01 | I39: ○ | J39: 0.0020833333
B40: =master!B29 -> CDKとは？ | C40: =master!C29 -> 26．AWS、Azure、Google Cloudの違い 【コラム】 | D40: ■主要パブリッククラウド3社の特徴まとめ 現在の主要パブリッククラウドサービスであるAmazon Web Services（AWS）、Microsoft Azure、Google Cloudは、それぞれ強みの分野が異なる。 ■Amazon Web Services（AWS） AWSはサービス数が非常に多く、機能の豊富さとグローバル展開に強みを持つ。 また、セキュリティと信頼性が高く、あらゆる業種・規模のシステムに対応できる総合型クラウドである。 コスト最適化の選択肢も豊富で、最も汎用性の高いクラウドといえる。 ■Microsoft Azure AzureはMicrosoft製品（Windows Server、Active Directory、Microsoft 365など）との親和性が高い点が最大の特徴である。 オンプレミス環境との連携（ハイブリッドクラウド）にも強く、企業システムとの統合に適している。 また、AI・データ分析分野にも強みを持つ。 ■Google Cloud Google Cloudはデータ分析とAI・機械学習領域に強みを持つクラウドである。 BigQueryやVertex AIなどの先進的なサービスが充実しており、データ活用や分析基盤として高く評価されている。 また、Kubernetesの開発元としてコンテナ技術にも強い。 | G40: ・AI-01 | I40: ○ | J40: 0.0020833333
C41: =master!C30 -> 27．Infrastructure as Code (IaC) とは？ | D41: IaC（Infrastructure as Code）とは、クラウドが提供するツールを用いて、サーバーやネットワークなどのインフラ構成をコードとして記述し、環境構築や管理を自動化する仕組みである。 これにより、手作業ではなくコードベースでインフラを再現可能にし、環境構築の効率化や品質向上を実現する。 ■マネジメントコンソール・CLIとの比較 従来のマネジメントコンソールによる手動操作や、CLI・SDKを用いた手続き型スクリプトには、以下のような課題がある。 〇主な課題 ・現在の構成状態が把握しづらく、リリース判断が難しい ・人による解釈の違いや操作ミスが発生しやすい ・同じ構成を何度も再現するのが困難 ・手順書やスクリプトの作成に時間がかかる ・継続的な更新やテストが難しく、内容が陳腐化しやすい ・リソース状態依存の判断やエラー処理、ロールバックを網羅しづらい | G41: ・AI-01 | I41: ○ | J41: 0.0034722222
C42: =master!C31 -> 28．IaCのメリット | D42: ■コスト削減 ・手順書の作成・メンテナンス・引き継ぎにかかるコストを削減できる ・手順書と実環境の乖離によるブラックボックス化を防止できる ・デプロイ作業時間を削減できる ・必要なときにリソースを作成し、不要時にまとめて破棄できるため、運用コストを最適化できる ■スピードアップ ・CI/CDと組み合わせることで、自動テスト・自動デプロイが可能になる ・変更内容を予測可能にし、頻繁なデプロイを実現できる ・同じ構成を何度でも迅速にデプロイできる ・構成パターンやベストプラクティスをチーム内で共有しやすい ■リスク低減 ・人的ミス（手作業ミス）を排除できる ・バージョン管理により変更履歴の追跡と承認プロセスを実現できる ・Gitリポジトリを「信頼できる唯一の情報源（Single Source of Truth）」として扱える ・必要に応じて過去バージョンへロールバックできる | G42: ・AI-01 | I42: ○ | J42: 0.0020833333
C43: =master!C32 -> 29．IaCを実現するためのAWSサービス | D43: ■AWS CloudFormation AWS CloudFormationは、テキスト形式（JSON / YAML）で宣言的に記述されたテンプレートからAWSリソースを作成するIaCサービスである。 インフラ構成をコードとして定義することで、環境の再現性や自動化を実現できる。 ■AWS CDK（Cloud Development Kit） AWS CDKは、AWSのインフラ環境をJavaやTypeScriptなどの一般的なプログラミング言語で記述できるツールキットである。 内部的にはAWS CloudFormationを利用しており、最終的にはCloudFormationテンプレートに変換されてリソースが作成される。 ■AWS CDK誕生の背景 Amazon.comの検索システムを再構築し、トレンド商品をリアルタイムに特定するという大規模な要件の中で、従来のCloudFormationには以下の課題があった。 ・複数チームが独立して開発・デプロイできるようにモジュール化したい ・繰り返し複雑な構成を作成する負担を減らすために抽象化したい ・JSONやYAMLのような設定言語ではなく、開発者が慣れた言語で表現したい これらの課題を解決するために、オブジェクト指向のライブラリとしてAWS CDKが開発された。 | G43: ・AI-01 | I43: ○ | J43: 0.0020833333
C44: =master!C33 -> 30．AWS CDKのメリット | D44: ■開発者体験の改善 ・アプリケーションと同じプログラミング言語で記述できるため、ドメイン固有言語（特定用途のためだけに作られた言語）の習得が不要 ・ソフトウェア開発の標準的な技法・プラクティス・ツールをそのまま活用できる ・型付けやバリデーションにより、早い段階でエラーを検知できる ・リソース間の依存関係やスタックの関係を自動的に解決できる ■アプリケーション全体をコードで管理 ・インフラだけでなく、Lambda関数のコードやコンテナイメージなどもまとめて管理できる ・CI/CDパイプラインをコードとして定義し、自動構築できる ・複数のAWSアカウントや環境（開発・検証・本番）を一元的に管理できる ■高レベルな抽象化 ・複雑なAWS設定を抽象化し、コード量と学習コストを削減できる ・必要に応じて抽象化を外し、個別リソースの詳細設定にもアクセス可能 ・ベストプラクティスに基づくデフォルト設定が提供される ・チーム内で構成パターンやガードレール（安全な範囲から外れないようにあらかじめ設定されたルールや制約）を共有・再利用できる | G44: ・AI-01 | I44: ○ | J44: 0.0034722222
C45: =master!C34 -> 31．AWS CDKの仕組み | D45: AWS CDKは、プログラミング言語を用いてインフラ構成を定義できるIaCツールである。 AWS CDK Toolkitにより、定義されたコードからCloudFormationテンプレートが合成（synthesize）され、そのテンプレートをもとにクラウド環境へ自動的に反映される。 また、作成されたインフラは「スタック」として管理され、定義したテンプレートと実際の状態を対応付けることで、同じ構成を繰り返し再現することが可能となる。 ■AWS CDKの利用手順 まず開発者は、TypeScript・JavaScript・Python・Java・C#・Goなどのプログラミング言語を使って、インフラ構成をコードとして定義する。これらの言語では各種コンストラクタライブラリを利用して、AWSリソース（Lambda、S3など）を記述できる。 次に、cdk deploy コマンドを実行すると、AWS CDK Toolkit（CLI）が起動する。CDK ToolkitはNode.js上で動作し、アプリケーションコードを解析してCloudFormationテンプレートへ変換（synthesize）する。 生成されたCloudFormationテンプレートはAWS CloudFormationに渡され、CloudFormationがその内容をもとにスタックとして管理する。ここでは「既に存在するか」「差分があるか」を判断しながら、必要なリソース操作（作成・更新・削除）を自動的に実行する。 CloudFormationは内部的にAWS APIを呼び出し、実際のクラウドリソース（Lambda関数、S3バケット、コンテナ、その他のAWSサービス）を構築することで、最終的に定義された状態へと収束させる。 また、Lambdaのコードやコンテナイメージなどのアセット（コードやファイルなどの成果物）もまとめてバンドルされ、CloudFormation経由でデプロイされる点も特徴である。 | G45: ・AI-01 | I45: ○ | J45: 0.0034722222
C46: =master!C35 -> 32．AWS CloudFormationとの違い | D46: ■AWS CloudFormationの場合 スタック間の依存関係を考慮しながらデプロイ順序を設計する必要がある。そのため、AWSリソースの構造をそのままテンプレートとして把握しやすい一方で、スタック数が増えると依存関係の管理が複雑になりやすい。 ■AWS CDKの場合 プログラミング言語を用いてインフラを定義するため、依存関係はCDKが自動的に解釈して解決する。その結果、複数のスタックをまとめて一括でデプロイでき、開発者は依存順序を意識せずにインフラ構成を記述できる。 | G46: ・AI-01 | I46: ○ | J46: 0.0020833333
C47: =master!C36 -> 33．クラウド移⾏時の7つの⽅式 | D47: オンプレミスのシステムをパブリッククラウドへ移行する際、既存の仕組みをできるだけそのままクラウドへ移行する方法を「リフト＆シフト」と呼ぶ。一方で、既存の仕組みを見直し、クラウド環境に最適化した形でシステムを構築・移行する方法を「クラウドネイティブ移行」と呼ぶ。 リフト＆シフトに分類される移行方式として、「Rehost（リホスト）」と「Relocate（リロケート）」がある。Rehostは、アプリケーションやOSを大きく変更することなく、そのままクラウドへ移行する方式である。Relocateは、VMwareなどの仮想化基盤を利用しているシステムを、仮想マシンごとクラウドへ移行する方式である。 クラウドネイティブ移行に分類される移行方式として、「Replatform（リプラットフォーム）」と「Refactor（リファクタ）」がある。Replatformは、アプリケーションの構造は大きく変更せず、OSやデータベースなどのミドルウェアをクラウド向けに変更・アップグレードして移行する方式である。Refactorは、クラウドの特性を最大限活用するために、アプリケーションそのものを設計・実装レベルから見直して作り直す方式である。 | G47: ・AI-01 | I47: ○ | J47: 0.0020833333
C48: =master!C37 -> 34．移行イメージ | D48: ■Rehost（リホスト）／Relocate（リロケート）：単純移行 OSやアプリケーション、データベースに大きな変更を加えず、既存システムをそのままクラウド環境へ移行する方式。 ■Replatform（リプラットフォーム）：プラットフォームの更新 アプリケーションは大きく変更せず、OSやデータベースを変更・アップグレードしながら、クラウド上の仮想サーバーやマネージドサービスへ移行する方式。 ■Refactor（リファクタ）：アプリケーションの再設計・書き換え クラウドの特性を最大限活用するため、アプリケーションをマイクロサービス化するなど設計から見直し、クラウドネイティブなサービスを活用した構成へ移行する方式。 | G48: ・AI-01 | I48: ○ | J48: 0.0020833333
C49: =master!C38 -> 35．ReplatformとRefactorの比較 | D49: ■Replatform（リプラットフォーム） クラウドのマネージドサービスを活用することで、ユーザー側の運用負荷を軽減できる移行方式である。 ただし、EC2などの仮想サーバーを利用する場合は、OSやミドルウェアのパッチ適用や設定変更など、一部の運用・管理は引き続き利用者が実施する必要がある。 ■Refactor（リファクタ） クラウドネイティブなサービスを活用することを前提に、アプリケーションやアーキテクチャを再設計する移行方式である。 サーバーレスサービスやフルマネージドサービスを活用することで、OSやミドルウェアの管理を不要にし、利用者はビジネス価値の創出に直結する開発業務へ注力できる。 また、運用負荷の削減やコスト最適化など、クラウドのメリットを最大限に享受できる。 | G49: ・AI-01 | I49: ○ | J49: 0.0020833333
B50: =master!B39 -> ガバクラとは？ | C50: =master!C39 -> 36．ガバメントクラウドとは？ | D50: ガバメントクラウドは、デジタル庁が整備した政府共通のクラウド利用基盤である。 中央政府や地方公共団体などが共通のクラウド環境を利用することで、システムの迅速な構築、柔軟な拡張、高いセキュリティの確保、そしてコスト削減を実現することを目的としている。 | G50: ・AI-01 | I50: ○ | J50: 0.0013888889
C51: =master!C40 -> 37．ガバメントクラウド対象 | D51: 「政府情報システムにおけるクラウドサービスの適切な利用に係る基本方針」では、極秘情報や高度な機密情報を取り扱う一部の政府情報システムを除き、政府情報システムは原則としてガバメントクラウドを利用する方針となっている。 現在、ガバメントクラウドとして採択されているパブリッククラウドサービスは5つあり、各府省庁や地方公共団体はこれらのクラウドサービスを利用してシステムを構築する。 ・Amazon Web Services（AWS） ・Microsoft（Microsoft Azure） ・Oracle（Oracle Cloud Infrastructure：OCI） ・Google（Google Cloud） ・さくらインターネット（さくらのクラウド） デジタル庁は、ガバメントクラウド全体の運営主体として、クラウド利用に関するガバナンスやセキュリティ基準を策定・統制し、安全かつ効率的なシステム運用を支援している。 | G51: ・AI-01 | I51: ○ | J51: 0.0020833333
C52: =master!C41 -> 38．ガバナンスとセキュリティ | D52: ■ガバナンス実現サービス ガバメントクラウドでは、ガバメントクラウドテンプレートを利用することで、ガバナンスやセキュリティに関する設定をAWS環境へ自動的に適用できる。これにより、各利用者は共通のセキュリティ基準に従った環境を容易に構築できる。 ■予防的統制（Preventive Control） 利用者がセキュリティポリシーに反する設定を行えないよう制御する。 データの国内保管を実現するため、利用可能なリージョンを東京リージョンおよび大阪リージョンに制限する。 デジタル庁が統制困難と判断した一部サービスの利用を禁止する。 ・AWS CloudShell ・AWS Outposts ・AWS Marketplace（利用時は個別相談） AWSアカウントへのサインイン時に多要素認証（MFA）を必須とする。 自治体業務システムを稼働させるAWSアカウントでは、インターネットゲートウェイ（IGW）のアタッチを禁止し、直接インターネットへ接続できないよう制御する。 ■発見的統制（Detective Control） セキュリティ上のリスクがある設定や運用状況を継続的に監視し、セキュリティポリシーに違反する設定を自動的に検出する。 検出した内容はSlackやメールを通じて利用者へ通知し、迅速な是正対応を促す。 このように、ガバメントクラウドでは「予防的統制」によって問題のある設定を未然に防ぎ、「発見的統制」によって設定ミスや運用上の問題を早期に発見することで、安全なクラウド利用を実現している。 | G52: ・AI-01 | I52: ○ | J52: 0.0020833333
C53: =master!C42 -> 39．ガバメントクラウドテンプレート | D53: ■ガバメントクラウドのテンプレート ・自動適用テンプレート（ガバナンスベース） デジタル庁がAWSアカウントを払い出す際に自動的に適用するテンプレートである。ガバナンスやセキュリティの基本統制を実現するための設定が含まれている。 ・必須適用テンプレート（ガバナンスベース） ガバメントクラウドを利用する組織が、払い出されたAWSアカウントに対して必ず適用するテンプレートである。組織のシステムがガバメントクラウドのセキュリティ要件や運用ルールに準拠するために利用される。 ・サンプルテンプレート システム構築時に参考として利用できるテンプレートである。利用者は業務要件に応じてカスタマイズしながら適用し、効率的にインフラ環境を構築できる。 環境払い出し時 → 自動適用テンプレート 初回環境構築時 → 必須適用テンプレート 個別システム構築時 → サンプルテンプレート | G53: ・AI-01 | I53: ○ | J53: 0.0013888889
C54: =master!C43 -> 40．マネージドサービスの活用 | D54: ガバメントクラウドでは、ELB、ECS、RDS、S3、CloudWatchなどのマネージドサービスを中心としたアーキテクチャを推奨している。例えば、利用者からのアクセスをELBで負荷分散し、ECS上で稼働するWeb APIコンテナが処理を行い、データはRDSやS3に保存する。また、CloudWatchによる監視やアラート通知を活用することで、システムの運用負荷を軽減できる。 さらに、GitHubとCI/CDパイプラインを活用した自動デプロイを実現することで、インフラ構成やアプリケーションの変更を効率的に管理できる。これにより、利用者はサーバーやミドルウェアの管理に費やす時間を削減し、システム開発や運用の効率化を図ることができる。 また、LambdaやAPI Gatewayなどのフルマネージドサービスを活用することで、サーバー管理を不要としたクラウドネイティブなシステムを構築できる。その結果、アプリケーションの開発からリリースまでの時間を短縮し、利用者はインフラ運用ではなく、住民サービスの向上や業務改善などのビジネス価値創出に注力できる。 | G54: ・AI-01 | I54: ○ | J54: 0.0013888889
C55: =master!C44 -> 41．リアーキテクチャとは？ | D55: ガバメントクラウドへのシステム移行では、移行パターンとして主にR1（Replatform） と R2（Rebuild） の2つが定義されている。これらは一般的なクラウド移行における Replatform および Refactor（Re-architect） に相当する。 R1（Replatform） は、既存システムの構成を大きく変更せず、OSやデータベースの更新、マネージドサービスの活用などを行いながらクラウドへ移行する方式である。ガバメントクラウドでは、R1はあくまで第一段階の移行と位置付けられており、将来的にR2へ移行することを前提としている。 R2（Rebuild） は、クラウドネイティブなアーキテクチャを前提としてシステムを再構築する方式である。 マイクロサービスアーキテクチャやフロントエンド・バックエンド分離を基本形とし、ECS、RDS、S3などのマネージドサービスや、Lambda、API Gatewayなどのフルマネージドサービスを活用することで、運用負荷の軽減と開発効率の向上を実現する。 そのため、R2への移行では既存システムの構成や機能を正確に把握したうえで、クラウドネイティブな設計へ見直すリアーキテクチャ（再設計）の考え方と手法を理解し、適用することが重要となる。 ガバメントクラウドでは、まずR1でクラウドへ移行し、その後R2によってクラウドネイティブなアーキテクチャへ段階的に進化させることを目指している。 | G55: ・AI-01 | I55: ○ | J55: 0.0020833333
C56: =master!C45 -> 42．リアーキテクチャの重要性 | D56: 従来のクラウド移行では、オンプレミス環境の構成を大きく変更せずにクラウドへ移行する R1（Replatform） が主流であった。しかし近年は、運用コストの削減や開発スピードの向上、さらには継続的なサービス改善への要求が高まっており、システムのモダン化とコスト最適化を実現するために、R2（Rebuild）によるリアーキテクチャ の重要性が増している。 システムをクラウドネイティブなアーキテクチャへ再設計することで、クラウドが持つ 可用性、弾力性（スケーラビリティ）、自動化 といった特性を最大限に活用できる。また、マネージドサービスやフルマネージドサービスを活用することで、インフラの構築・運用にかかるコストや工数を削減しながら、セキュリティ品質の向上、開発サイクルの高速化、継続的な機能改善を実現できる。 一方で、単にオンプレミス環境をクラウドへ移行するだけでは、運用方法やシステム構成が従来のままとなり、クラウドのメリットを十分に活用できない。そのため、クラウド移行の効果を最大化するためには、リアーキテクチャによるクラウドネイティブ化が重要となる。 クラウド移行のゴールはサーバーの移設ではなく、リアーキテクチャによってクラウドネイティブなシステムへ進化させることである。 | G56: ・AI-01 | I56: ○ | J56: 0.0020833333
C57: =master!C46 -> 43．リアーキテクチャの実施プロセス | D57: AWSでは、アプリケーションのモダナイゼーションを 「評価（Assess）」「モダナイズ（Modernize）」「管理（Manage）」 の3つのフェーズで整理している。 ■評価（Assess）フェーズで Application Rationalization Assessment により既存システムやアプリケーション資産の棚卸しを行い、システム構成や技術的負債、移行上の制約を整理する。また、Modernization Roadmap を作成し、移行対象や優先順位、移行方式を明確にしたうえで、段階的なモダナイゼーション計画を策定する。 ■モダナイズ（Modernize）フェーズ Application Modernization Projects を実施し、アプリケーションのリファクタリングやリアーキテクチャを進める。マイクロサービス化やフロントエンド・バックエンド分離、コンテナ化、マネージドサービスやフルマネージドサービスの活用などを通じて、クラウドネイティブなアーキテクチャへ移行し、品質と生産性の向上を実現する。 ■管理（Manage）フェーズ ITガバナンスの統制のもとでシステムを運用し、継続的な改善や最適化を行う。 「何を移行するかを評価（Assess）し、どのようにクラウドネイティブ化するかを計画し（Roadmap）、実際に再構築する（Modernize）」という流れが、リアーキテクチャ成功の鍵となる。 | G57: ・AI-01 | I57: ○ | J57: 0.0020833333
C58: =master!C47 -> 44．リアーキテクチャの手法 | D58: ★アプリケーションのリファクタリング ■モノリスの分解 信頼性やパフォーマンスに課題があり、複数の機能が密結合したモノリシックアプリケーションを特定する。 その後、業務ドメインや機能単位でアプリケーションを分割し、複数の独立したマイクロサービスへ変換する。 これにより、サービスごとの独立した開発・デプロイ・スケーリングが可能となり、保守性や拡張性を向上できる。 ■マイクロサービスの統合 分割したマイクロサービス同士を適切に連携させることも重要である。 連携方法が不適切な場合、データ損失やレイテンシの増加、データ整合性の問題が発生する可能性がある。 そのため、API Gatewayパターンやメッセージングパターン、Pub/Subパターンなどを利用してサービス間を統合し、複数のマイクロサービスが一つのシステムとして連携して動作できるようにする。 ★クラウド基盤のモダン化 ■サーバレスサービスの活用 自律性とスケーラビリティを備えたFaaS（Function as a Service）などのサーバレスサービスを活用することで、マイクロサービスの実行基盤を効率的に構築できる。 サーバーの運用管理が不要となるため、開発者はアプリケーション開発に集中でき、需要に応じた自動スケーリングも実現できる。 ■IaCによる基盤サービスの構築 IaC（Infrastructure as Code）を活用し、インフラリソースをコードとして管理することで、環境構築の再現性を確保するとともに、自動化を実現する。 さらに、CI/CDパイプラインに組み込むことで、アプリケーションの変更に合わせたインフラ変更を迅速に反映でき、リードタイムの短縮や運用効率の向上につながる。例えば、AWSではCloudFormationやAWS CDKを利用してIaCを実現できる。 | G58: ・AI-01 | I58: ○ | J58: 0.0020833333
C59: =master!C48 -> 45．本講義のまとめ | D59: これまでの内容に合わせて説明する。 | G59: ・AI-01 | I59: ○ | J59: 0.0034722222
C60: =master!C49 -> 46．AWS CDKの講師デモ | D60: ファイルの内容をCloudShell上で実施する。 ※CDKを利用するので時間がかかる。 | G60: ・AI-01 ・AI-02 ・AI-03 | I60: △ | J60: 0.013888889 | K60: ※時間が不足した場合は割愛してください。
C61: =master!C50 -> 47．AWS 豆知識 【コラム】 | D61: 以下は解答です。 Amazon 〇〇：AWS初期から存在するサービスに多い。 AWS △△：比較的新しいサービスに多い。 接頭語なし：Fargate、Glue、Athena などがある。 ※厳密な命名ルールがあるわけではなく、サービスごとのブランド戦略や登場時期によって決められている。 | G61: ・AI-01 | I61: △ | J61: 0.0034722222 | K61: ※時間が不足した場合は割愛してください。

Sheet master
B1: AI Native-AWS
B2: 章の名称 | C2: 節の名称
B4: クラウドとは？ | C4: １．IT業界の歴史
C5: ２．クラウドの市場価値向上
C6: ３．クラウドとは？
C7: ４．オンプレミスとのコスト比較
C8: ５．クラウドの特徴
C9: ６．クラウドの特徴2
C10: ７．アベイラビリティゾーンとリージョン
C11: ８．クラウドにおける責任共有モデル
C12: ９．NTTデータはデータセンターが得意 【コラム】
B13: AWSとは？ | C13: 10．AWSとは？
C14: 11．AWSの利用産業
C15: 12．Web3層アーキテクチャ
C16: 13．AWSの基本アーキテクチャ
C17: 14．Amazon VPC（Virtual Private Cloud）
C18: 15．Amazon EC2（Elastic Compute Cloud）
C19: 16．Amazon RDS（Relational Database Service）
C20: 17．マネージドサービスとは？
C21: 18．ELB（Elastic Load Balancing）
C22: 19．Amazon S3（Simple Storage Service）
C23: 20．Amazon CloudWatch
C24: 21．コンピューティングサービス
C25: 22．コンテナとは？
... C28: 25．その他の周辺サービス
B29: CDKとは？ | C29: 26．AWS、Azure、Google Cloudの違い 【コラム】
C30: 27．Infrastructure as Code (IaC) とは？
C31: 28．IaCのメリット
C32: 29．IaCを実現するためのAWSサービス
C33: 30．AWS CDKのメリット
C34: 31．AWS CDKの仕組み
C35: 32．AWS CloudFormationとの違い
C36: 33．クラウド移⾏時の7つの⽅式
C37: 34．移行イメージ
C38: 35．ReplatformとRefactorの比較
B39: ガバクラとは？ | C39: 36．ガバメントクラウドとは？
C40: 37．ガバメントクラウド対象
C41: 38．ガバナンスとセキュリティ
C42: 39．ガバメントクラウドテンプレート
C43: 40．マネージドサービスの活用
C44: 41．リアーキテクチャとは？
C45: 42．リアーキテクチャの重要性
C46: 43．リアーキテクチャの実施プロセス
C47: 44．リアーキテクチャの手法
C48: 45．本講義のまとめ
C49: 46．AWS CDKの講師デモ
C50: 47．AWS 豆知識 【コラム】
